quandl_fund_xlsx/__init__.py
quandl_fund_xlsx/api_key.py
quandl_fund_xlsx/cli.py
quandl_fund_xlsx/fundamentals.py
quandl_fund_xlsx-0.1.4.dist-info/DESCRIPTION.rst
quandl_fund_xlsx-0.1.4.dist-info/METADATA
quandl_fund_xlsx-0.1.4.dist-info/RECORD
quandl_fund_xlsx-0.1.4.dist-info/WHEEL
quandl_fund_xlsx-0.1.4.dist-info/entry_points.txt
quandl_fund_xlsx-0.1.4.dist-info/metadata.json
quandl_fund_xlsx-0.1.4.dist-info/top_level.txt
