Metadata-Version: 2.0
Name: quandl-fund-xlsx
Version: 0.1.4
Summary: A CLI tool which uses the Quandl Fundmentals API and writes results to Excel Spreadsheets.
Home-page: https://github.com/robren/quandl_fund_xlsx
Author: Robert Rennison
Author-email: rob@robren.net
License: Apache Software License 2.0
Keywords: quandl_fund_xlsx quandl finance
Platform: UNKNOWN
Classifier: Development Status :: 2 - Pre-Alpha
Classifier: Intended Audience :: Developers
Classifier: License :: OSI Approved :: Apache Software License
Classifier: Natural Language :: English
Classifier: Programming Language :: Python :: 2.7
Classifier: Programming Language :: Python :: 3
Classifier: Programming Language :: Python :: 3.3
Classifier: Programming Language :: Python :: 3.4
Classifier: Programming Language :: Python :: 3.5
Requires-Dist: docopt (>=0.6.0)
Requires-Dist: pandas
Requires-Dist: quandl
Requires-Dist: xlsxwriter
Requires-Dist: mock
